{
  "id": "19e5ef0d-6e02-4f11-8547-75020d098c8a",
  "file_path": "./kotadb-data/cli-dogfood/storage/documents/19e5ef0d-6e02-4f11-8547-75020d098c8a.md",
  "original_path": "self/kota-db/files/clients/python/tests/test_client.py",
  "title": "File: clients/python/tests/test_client.py",
  "size": 11362,
  "created": 1757516939,
  "updated": 1757516939,
  "hash": [
    51,
    117,
    80,
    26,
    248,
    171,
    19,
    130,
    128,
    173,
    85,
    31,
    77,
    186,
    43,
    15,
    21,
    229,
    197,
    212,
    225,
    172,
    108,
    34,
    72,
    169,
    94,
    90,
    105,
    52,
    141,
    140
  ],
  "embedding": null
}