{
  "id": "6b2fea72-19f2-493c-92a4-37b35b7cb6cf",
  "file_path": "./kotadb-data/cli-dogfood/storage/documents/6b2fea72-19f2-493c-92a4-37b35b7cb6cf.md",
  "original_path": "self/kota-db/files/src/wrappers/optimization.rs",
  "title": "File: src/wrappers/optimization.rs",
  "size": 22434,
  "created": 1757516940,
  "updated": 1757516940,
  "hash": [
    14,
    77,
    218,
    191,
    251,
    2,
    74,
    234,
    249,
    218,
    53,
    195,
    219,
    97,
    116,
    91,
    234,
    86,
    103,
    246,
    200,
    6,
    163,
    130,
    198,
    230,
    197,
    24,
    232,
    118,
    145,
    4
  ],
  "embedding": null
}