{
  "id": "eda6253f-8aff-4ab3-a0f9-37b74853a7c1",
  "file_path": "./kotadb-data/cli-dogfood/storage/documents/eda6253f-8aff-4ab3-a0f9-37b74853a7c1.md",
  "original_path": "self/kota-db/files/src/symbol_storage.rs",
  "title": "File: src/symbol_storage.rs",
  "size": 96621,
  "created": 1757516940,
  "updated": 1757516940,
  "hash": [
    76,
    211,
    230,
    189,
    224,
    178,
    221,
    250,
    205,
    242,
    183,
    17,
    195,
    219,
    145,
    33,
    172,
    72,
    72,
    23,
    118,
    199,
    45,
    242,
    63,
    201,
    205,
    164,
    80,
    38,
    23,
    76
  ],
  "embedding": null
}