{
  "id": "2aa8ddda-b83e-45c5-bc9f-1aa2e5546c13",
  "file_path": "./kotadb-data/dogfood-http/storage/documents/2aa8ddda-b83e-45c5-bc9f-1aa2e5546c13.md",
  "original_path": "self/kota-db/files/src/metrics/performance.rs",
  "title": "File: src/metrics/performance.rs",
  "size": 18098,
  "created": 1757547170,
  "updated": 1757547170,
  "hash": [
    124,
    232,
    140,
    182,
    198,
    220,
    41,
    66,
    55,
    135,
    163,
    225,
    252,
    167,
    1,
    180,
    250,
    192,
    186,
    116,
    124,
    8,
    80,
    211,
    169,
    199,
    226,
    126,
    169,
    71,
    70,
    194
  ],
  "embedding": null
}