{
  "id": "48f74ca7-eb14-4c9d-9424-cbc8e1368250",
  "file_path": "./kotadb-data/dogfood-http/storage/documents/48f74ca7-eb14-4c9d-9424-cbc8e1368250.md",
  "original_path": "self/kota-db/files/tests/adversarial_tests.rs",
  "title": "File: tests/adversarial_tests.rs",
  "size": 32548,
  "created": 1757547426,
  "updated": 1757547426,
  "hash": [
    116,
    36,
    78,
    67,
    225,
    110,
    66,
    151,
    43,
    175,
    53,
    70,
    131,
    116,
    134,
    255,
    23,
    11,
    73,
    152,
    140,
    249,
    178,
    199,
    188,
    24,
    106,
    165,
    233,
    112,
    110,
    74
  ],
  "embedding": null
}