{
  "id": "9144e332-234a-4eb7-9198-cf7b5b64155b",
  "file_path": "./kotadb-data/dogfood-http/storage/documents/9144e332-234a-4eb7-9198-cf7b5b64155b.md",
  "original_path": "self/kota-db/files/scripts/dev/docker-dev.sh",
  "title": "File: scripts/dev/docker-dev.sh",
  "size": 5708,
  "created": 1757547170,
  "updated": 1757547170,
  "hash": [
    236,
    211,
    66,
    225,
    5,
    11,
    92,
    246,
    49,
    249,
    81,
    109,
    186,
    31,
    124,
    93,
    204,
    88,
    254,
    85,
    165,
    93,
    42,
    200,
    149,
    183,
    162,
    148,
    106,
    166,
    101,
    180
  ],
  "embedding": null
}