{
  "id": "94b8be13-bfb7-4f3c-b192-e522bca5b7bc",
  "file_path": "./kotadb-data/dogfood-http/storage/documents/94b8be13-bfb7-4f3c-b192-e522bca5b7bc.md",
  "original_path": "self/kota-db/files/mkdocs.yml",
  "title": "File: mkdocs.yml",
  "size": 4540,
  "created": 1757547280,
  "updated": 1757547280,
  "hash": [
    4,
    213,
    236,
    219,
    45,
    89,
    46,
    45,
    63,
    57,
    154,
    209,
    228,
    229,
    93,
    191,
    91,
    110,
    118,
    243,
    35,
    151,
    2,
    38,
    120,
    188,
    124,
    123,
    233,
    83,
    66,
    104
  ],
  "embedding": null
}