{
  "id": "fb12e789-7f38-4721-b1f3-7916ec27897f",
  "file_path": "./kotadb-data/dogfood-http/storage/documents/fb12e789-7f38-4721-b1f3-7916ec27897f.md",
  "original_path": "self/kota-db/files/src/database.rs",
  "title": "File: src/database.rs",
  "size": 20545,
  "created": 1757547426,
  "updated": 1757547426,
  "hash": [
    185,
    212,
    202,
    159,
    118,
    118,
    7,
    192,
    64,
    39,
    113,
    219,
    217,
    226,
    92,
    88,
    140,
    220,
    10,
    126,
    72,
    211,
    124,
    58,
    18,
    189,
    117,
    124,
    216,
    2,
    53,
    236
  ],
  "embedding": null
}