{
  "id": "602a7662-3f45-4181-bea5-94678d8a091b",
  "file_path": "./examples-data/personal-kb/documents/602a7662-3f45-4181-bea5-94678d8a091b.md",
  "original_path": "/generated/doc-045.md",
  "title": "Generated Document 45",
  "size": 202,
  "created": 1754607754,
  "updated": 1754607754,
  "hash": [
    11,
    191,
    0,
    35,
    115,
    240,
    50,
    126,
    32,
    195,
    126,
    191,
    195,
    125,
    236,
    134,
    172,
    182,
    120,
    249,
    71,
    229,
    61,
    203,
    69,
    157,
    168,
    127,
    155,
    144,
    6,
    109
  ],
  "embedding": null
}