{
  "id": "69954f85-35d7-44af-9bd3-59271d44d9be",
  "file_path": "./kotadb-data/dogfood/storage/documents/69954f85-35d7-44af-9bd3-59271d44d9be.md",
  "original_path": "self/kota-db/files/tests/test_symbol_index.rs",
  "title": "File: tests/test_symbol_index.rs",
  "size": 11338,
  "created": 1757516908,
  "updated": 1757516908,
  "hash": [
    127,
    34,
    102,
    64,
    164,
    234,
    97,
    112,
    234,
    251,
    255,
    92,
    28,
    17,
    181,
    42,
    115,
    232,
    145,
    69,
    162,
    118,
    104,
    1,
    95,
    15,
    99,
    191,
    31,
    136,
    161,
    99
  ],
  "embedding": null
}