{
  "id": "70054847-1d3c-4fe3-9788-7c972c242fc9",
  "file_path": "./kotadb-data/dogfood/storage/documents/70054847-1d3c-4fe3-9788-7c972c242fc9.md",
  "original_path": "self/kota-db/files/src/contracts/performance.rs",
  "title": "File: src/contracts/performance.rs",
  "size": 14647,
  "created": 1757516908,
  "updated": 1757516908,
  "hash": [
    219,
    196,
    7,
    115,
    176,
    38,
    98,
    246,
    201,
    251,
    113,
    203,
    96,
    230,
    233,
    186,
    109,
    153,
    73,
    81,
    189,
    83,
    109,
    177,
    199,
    178,
    16,
    23,
    226,
    220,
    154,
    35
  ],
  "embedding": null
}