{
  "id": "510809da-22e0-4a80-897f-2487e44a7fc4",
  "file_path": "./kotadb-data/storage/documents/510809da-22e0-4a80-897f-2487e44a7fc4.md",
  "original_path": "repos/kota-db/files/clients/python/tests/test_server_real.py",
  "title": "File: clients/python/tests/test_server_real.py",
  "size": 17904,
  "created": 1757473562,
  "updated": 1757473562,
  "hash": [
    155,
    246,
    233,
    19,
    176,
    97,
    95,
    40,
    199,
    147,
    232,
    218,
    186,
    43,
    237,
    191,
    210,
    144,
    19,
    147,
    40,
    38,
    88,
    164,
    179,
    81,
    106,
    197,
    175,
    91,
    56,
    193
  ],
  "embedding": null
}