{
  "id": "a29f9663-079f-437a-973d-cf498a65f904",
  "file_path": "./kotadb-data/storage/documents/a29f9663-079f-437a-973d-cf498a65f904.md",
  "original_path": "repos/kota-db/files/clients/python/Makefile",
  "title": "File: clients/python/Makefile",
  "size": 5355,
  "created": 1757473562,
  "updated": 1757473562,
  "hash": [
    233,
    252,
    69,
    160,
    32,
    190,
    49,
    237,
    21,
    32,
    147,
    149,
    194,
    244,
    22,
    127,
    148,
    120,
    247,
    61,
    111,
    81,
    253,
    55,
    248,
    5,
    203,
    220,
    140,
    248,
    138,
    103
  ],
  "embedding": null
}